cassandra_reaper_api/__about__.py
cassandra_reaper_api/__init__.py
cassandra_reaper_api-0.0.1.dist-info/METADATA
cassandra_reaper_api-0.0.1.dist-info/WHEEL
cassandra_reaper_api-0.0.1.dist-info/licenses/LICENSE
cassandra_reaper_api-0.0.1.dist-info/RECORD
